LICENSE
ariarpc/__init__.py
ariarpc/py.typed
ariarpc-0.0.2.dist-info/LICENSE
ariarpc-0.0.2.dist-info/METADATA
ariarpc-0.0.2.dist-info/WHEEL
ariarpc-0.0.2.dist-info/RECORD
